randy-0.9.3.dist-info/METADATA
randy-0.9.3.dist-info/WHEEL
randy-0.9.3.dist-info/RECORD
randy-0.9.3.dist-info/top_level.txt
randy-0.9.3.dist-info/metadata.json
randy-0.9.3.dist-info/DESCRIPTION.rst
randy/__init__.py
randy/core.py
